fsdev/__init__.py
fsdev/__main__.py
fsdev/cli.py
fsdev/errors.py
fsdev/fs.py
fsdev/web.py
fsdev-0.1.2.dist-info/entry_points.txt
fsdev-0.1.2.dist-info/LICENSE
fsdev-0.1.2.dist-info/WHEEL
fsdev-0.1.2.dist-info/METADATA
fsdev-0.1.2.dist-info/RECORD
