Metadata-Version: 2.1
Name: fsdev
Version: 0.1.2
Summary: A super simple filesystem dev server
Home-page: https://trslater.ca/fsdev
License: MIT
Author: Tristan Slater
Author-email: hello@trslater.ca
Requires-Python: >=3.10,<4.0
Classifier: License :: OSI Approved :: MIT License
Classifier: Programming Language :: Python :: 3
Classifier: Programming Language :: Python :: 3.10
Requires-Dist: Jinja2 (>=3.0.3,<4.0.0)
Project-URL: Repository, https://github.com/trslater/fsdev
